{
    "name": "HController_Module",
    "sender": {
        "HController": {
            "PS3": {
                "leftx": 0,
                "lefty": 0,
                "rightx": 0,
                "righty": 0,
                "trig0": false,
                "trig1": false,
                "trig2": false,
                "trig3": false,
                "buttonup": false,
                "buttondown": false,
                "buttonleft": false,
                "buttonright": false,
                "triangle": false,
                "circle": false,
                "cross": false,
                "square": false,
                "select": false,
                "start": false,
                "ps": false
            },
            "Keyboard": {
                "z": false,
                "q": false,
                "s": false,
                "d": false,
                "p": false,
                "esc": false
            }
        }
    },
    "listener": []
}